AUTHORS.rst
CHANGES.rst
LICENSE.rst
MANIFEST.in
README.rst
setup.py
binning/__init__.py
interval_binning.egg-info/PKG-INFO
interval_binning.egg-info/SOURCES.txt
interval_binning.egg-info/dependency_links.txt
interval_binning.egg-info/pbr.json
interval_binning.egg-info/top_level.txt