Metadata-Version: 1.1
Name: interval-binning
Version: 1.0.0
Summary: A Python implementation of the interval binning scheme
Home-page: https://github.com/martijnvermaat/binning
Author: Martijn Vermaat
Author-email: martijn@vermaat.name
License: MIT License
Keywords: bioinformatics
Platform: any
Classifier: Development Status :: 3 - Alpha
Classifier: Intended Audience :: Developers
Classifier: Intended Audience :: Science/Research
Classifier: Operating System :: OS Independent
Classifier: Programming Language :: Python
Classifier: Programming Language :: Python :: 2
Classifier: Programming Language :: Python :: 2.6
Classifier: Programming Language :: Python :: 2.7
Classifier: Programming Language :: Python :: 3
Classifier: Programming Language :: Python :: 3.3
Classifier: Programming Language :: Python :: 3.4
Classifier: Topic :: Scientific/Engineering
